mlopsatt/__init__.py
mlopsatt/mlflow_registrator.py
mlopsatt/mlops_connector.py
mlopsatt/mlops_deployer.py
mlopsatt-0.1.0.dist-info/METADATA
mlopsatt-0.1.0.dist-info/WHEEL
mlopsatt-0.1.0.dist-info/RECORD
